<?xml version="1.0" encoding="UTF-8" standalone="yes"?>
<APIProxy revision="3" name="hello-world">
  <DisplayName>Hello World</DisplayName>
  <Description>An example API proxy.</Description>
  <CreatedAt>1766684086019</CreatedAt>
  <LastModifiedAt>1766711793587</LastModifiedAt>
  <BasePaths>/hello-world</BasePaths>
  <Policies>
    <Policy>AM-PrintUserDetails</Policy>
  </Policies>
  <ProxyEndpoints>
    <ProxyEndpoint>default</ProxyEndpoint>
  </ProxyEndpoints>
  <TargetEndpoints>
    <TargetEndpoint>default</TargetEndpoint>
  </TargetEndpoints>
</APIProxy>
